Pyewacket.cpython-38-darwin.so
Pyewacket-1.3.9.dist-info/LICENSE
Pyewacket-1.3.9.dist-info/METADATA
Pyewacket-1.3.9.dist-info/WHEEL
Pyewacket-1.3.9.dist-info/top_level.txt
Pyewacket-1.3.9.dist-info/RECORD
