Metadata-Version: 2.1
Name: Pyewacket
Version: 1.3.9
Summary: Drop-in Replacement for the Python Random Module.
Home-page: UNKNOWN
Author: Robert Sharp
Author-email: webmaster@sharpdesigndigital.com
License: Free for non-commercial use
Keywords: Pyewacket,random module replacement
Platform: Darwin
Platform: Linux
Classifier: Development Status :: 5 - Production/Stable
Classifier: Programming Language :: Python :: 3.6
Classifier: Programming Language :: Cython
Classifier: Programming Language :: C++
Classifier: Operating System :: MacOS :: MacOS X
Classifier: Operating System :: POSIX :: Linux
Classifier: Topic :: Software Development :: Libraries :: Python Modules
Requires-Python: >=3.6
